{"stats":{"minecraft:killed_by":{"minecraft:husk":1,"minecraft:skeleton":2},"minecraft:custom":{"minecraft:time_since_rest":4281,"minecraft:sprint_one_cm":7015,"minecraft:damage_taken":1055,"minecraft:walk_one_cm":165550,"minecraft:mob_kills":1,"minecraft:damage_dealt":40,"minecraft:interact_with_crafting_table":6,"minecraft:fly_one_cm":2052,"minecraft:open_chest":4,"minecraft:play_time":57417,"minecraft:deaths":3,"minecraft:jump":520,"minecraft:walk_on_water_one_cm":126,"minecraft:leave_game":2,"minecraft:time_since_death":46762,"minecraft:sleep_in_bed":5,"minecraft:total_world_time":57417,"minecraft:climb_one_cm":988,"minecraft:fall_one_cm":7971},"minecraft:used":{"minecraft:diorite":4,"minecraft:stone_sword":1,"minecraft:stone_shovel":52,"minecraft:bread":1,"minecraft:stone_pickaxe":142,"minecraft:chest":2,"minecraft:wooden_pickaxe":41,"minecraft:torch":3,"minecraft:oak_door":2,"toughasnails:water_canteen":2,"minecraft:stone_axe":19,"minecraft:orange_bed":4,"anthropology_items__structures:hunters_machete":5,"minecraft:dirt":10,"minecraft:cobblestone":1,"minecraft:crafting_table":1,"minecraft:andesite":2,"minecraft:spruce_fence":1},"minecraft:killed":{"minecraft:chicken":1},"minecraft:mined":{"minecraft:andesite":17,"treechop:chopped_log":4,"minecraft:grass":3,"minecraft:grass_block":6,"minecraft:spruce_fence":1,"minecraft:coal_ore":22,"minecraft:chest":1,"minecraft:sand":1,"minecraft:dirt":55,"minecraft:stone":132,"minecraft:oak_leaves":3,"minecraft:diorite":4,"minecraft:orange_bed":3},"minecraft:crafted":{"minecraft:oak_door":3,"minecraft:oak_planks":52,"minecraft:stone_shovel":1,"minecraft:crafting_table":1,"minecraft:stick":16,"minecraft:wooden_pickaxe":1,"minecraft:stone_pickaxe":3,"minecraft:chest":2,"minecraft:stone_sword":1,"minecraft:birch_planks":20,"minecraft:stone_axe":1},"minecraft:picked_up":{"minecraft:stripped_oak_log":1,"minecraft:birch_log":5,"minecraft:stick":9,"minecraft:chicken":1,"minecraft:feather":2,"minecraft:andesite":17,"minecraft:leather":4,"minecraft:torch":5,"minecraft:spruce_fence":1,"minecraft:sand":1,"anthropology_items__structures:hunters_machete":1,"minecraft:oak_log":13,"minecraft:diorite":4,"minecraft:shield":1,"minecraft:dirt":62,"minecraft:orange_bed":4,"toughasnails:water_canteen":1,"minecraft:apple":1,"minecraft:emerald":1,"minecraft:bread":19,"minecraft:oak_sapling":4,"minecraft:chest":1,"minecraft:birch_sapling":2,"minecraft:coal":22,"minecraft:cobblestone":132,"minecraft:egg":1}},"DataVersion":3465}